{"FmgID":34,"Fmg":{"Entries":[
{"ID":2000,"Text":"Cannot proceed until game is fully installed"},
{"ID":4000,"Text":"Contraption does not move"},
{"ID":4001,"Text":"Locked by some contraption"},
{"ID":4002,"Text":null},
{"ID":4003,"Text":null},
{"ID":4004,"Text":null},
{"ID":4005,"Text":null},
{"ID":4006,"Text":null},
{"ID":4007,"Text":null},
{"ID":4008,"Text":null},
{"ID":4009,"Text":null},
{"ID":4010,"Text":"Cannot open from this side"},
{"ID":4080,"Text":"The door is shut tight"},
{"ID":4100,"Text":"Return to entrance?"},
{"ID":4200,"Text":"Somewhere, a heavy door has opened"},
{"ID":4201,"Text":null},
{"ID":4202,"Text":null},
{"ID":4203,"Text":null},
{"ID":4204,"Text":null},
{"ID":4205,"Text":null},
{"ID":4206,"Text":null},
{"ID":4207,"Text":null},
{"ID":4208,"Text":null},
{"ID":4209,"Text":null},
{"ID":4210,"Text":"Guide and gatekeeper for those returning to the roots"},
{"ID":4300,"Text":"Travel to another location?"},
{"ID":6000,"Text":"Summon signs can now be sent to summoning pools"},
{"ID":20000,"Text":"Impenetrable thorns refuse all.\nNone may enter the Erdtree."},
{"ID":20001,"Text":null},
{"ID":20002,"Text":null},
{"ID":20003,"Text":"You cannot proceed without more Great Runes"},
{"ID":20004,"Text":"You cannot use this without more Great Runes"},
{"ID":20005,"Text":"Sealed by Morgott the Grace-Given"},
{"ID":20006,"Text":"You cannot proceed without a ring of oath"},
{"ID":20020,"Text":"You do not have the required medallion"},
{"ID":20021,"Text":"You do not have the required medallion"},
{"ID":20022,"Text":null},
{"ID":20023,"Text":null},
{"ID":20024,"Text":null},
{"ID":20025,"Text":null},
{"ID":20026,"Text":null},
{"ID":20027,"Text":null},
{"ID":20028,"Text":null},
{"ID":20029,"Text":null},
{"ID":20030,"Text":"You cannot proceed without a glintstone key"},
{"ID":20031,"Text":"You cannot proceed without a sealbreaker"},
{"ID":20032,"Text":null},
{"ID":20033,"Text":null},
{"ID":20034,"Text":null},
{"ID":20035,"Text":null},
{"ID":20036,"Text":null},
{"ID":20037,"Text":null},
{"ID":20038,"Text":null},
{"ID":20039,"Text":null},
{"ID":20040,"Text":"Something fits on this pedestal"},
{"ID":20041,"Text":null},
{"ID":20042,"Text":null},
{"ID":20043,"Text":null},
{"ID":20044,"Text":null},
{"ID":20045,"Text":null},
{"ID":20046,"Text":null},
{"ID":20047,"Text":null},
{"ID":20048,"Text":null},
{"ID":20049,"Text":null},
{"ID":20050,"Text":"Opens only to those carrying a finger"},
{"ID":20100,"Text":"Summon broken spirit?"},
{"ID":20200,"Text":"You must solve the puzzle to enter"},
{"ID":20201,"Text":null},
{"ID":20202,"Text":null},
{"ID":20203,"Text":null},
{"ID":20204,"Text":null},
{"ID":20205,"Text":null},
{"ID":20206,"Text":null},
{"ID":20207,"Text":null},
{"ID":20208,"Text":null},
{"ID":20209,"Text":null},
{"ID":20210,"Text":"The seal on the rise opened"},
{"ID":20300,"Text":"Enter evergaol?"},
{"ID":20400,"Text":null},
{"ID":20401,"Text":null},
{"ID":20402,"Text":null},
{"ID":20403,"Text":null},
{"ID":20404,"Text":null},
{"ID":20405,"Text":null},
{"ID":20406,"Text":null},
{"ID":20407,"Text":null},
{"ID":20408,"Text":null},
{"ID":20409,"Text":null},
{"ID":20410,"Text":null},
{"ID":20500,"Text":"Closed with an imp's seal"},
{"ID":20501,"Text":null},
{"ID":20502,"Text":null},
{"ID":20503,"Text":null},
{"ID":20504,"Text":null},
{"ID":20505,"Text":null},
{"ID":20506,"Text":null},
{"ID":20507,"Text":null},
{"ID":20508,"Text":null},
{"ID":20509,"Text":null},
{"ID":20510,"Text":"The imp's seal is in effect"},
{"ID":20600,"Text":"The Beast Eye quivers"},
{"ID":20700,"Text":"Ensnared in a transporter trap!"},
{"ID":30000,"Text":"A seal was broken in town somewhere"},
{"ID":30001,"Text":null},
{"ID":30002,"Text":null},
{"ID":30003,"Text":null},
{"ID":30004,"Text":null},
{"ID":30005,"Text":null},
{"ID":30006,"Text":null},
{"ID":30007,"Text":null},
{"ID":30008,"Text":null},
{"ID":30009,"Text":null},
{"ID":30010,"Text":"Power gathers somewhere in horned remains"},
{"ID":30011,"Text":null},
{"ID":30012,"Text":null},
{"ID":30013,"Text":null},
{"ID":30014,"Text":null},
{"ID":30015,"Text":null},
{"ID":30016,"Text":null},
{"ID":30017,"Text":null},
{"ID":30018,"Text":null},
{"ID":30019,"Text":null},
{"ID":30020,"Text":"A seal was broken in town"},
{"ID":30021,"Text":"Enter evergaol?"},
{"ID":30022,"Text":null},
{"ID":30023,"Text":"Held shut by a seal"},
{"ID":30024,"Text":null},
{"ID":30025,"Text":null},
{"ID":30026,"Text":null},
{"ID":30027,"Text":null},
{"ID":30028,"Text":null},
{"ID":30029,"Text":null},
{"ID":30030,"Text":"A seal was broken somewhere"},
{"ID":30031,"Text":"Held shut by a seal"},
{"ID":30032,"Text":null},
{"ID":30033,"Text":null},
{"ID":30034,"Text":null},
{"ID":30035,"Text":null},
{"ID":30036,"Text":null},
{"ID":30037,"Text":null},
{"ID":30038,"Text":null},
{"ID":30039,"Text":null},
{"ID":30040,"Text":"Cannot be used now"},
{"ID":30041,"Text":null},
{"ID":30042,"Text":null},
{"ID":30043,"Text":null},
{"ID":30044,"Text":null},
{"ID":30045,"Text":null},
{"ID":30046,"Text":null},
{"ID":30047,"Text":null},
{"ID":30048,"Text":null},
{"ID":30049,"Text":null},
{"ID":30050,"Text":"Blocked shut for now"},
{"ID":30051,"Text":"Blocked shut for now"},
{"ID":30052,"Text":null},
{"ID":30053,"Text":null},
{"ID":30054,"Text":null},
{"ID":30055,"Text":null},
{"ID":30056,"Text":null},
{"ID":30057,"Text":null},
{"ID":30058,"Text":null},
{"ID":30059,"Text":null},
{"ID":30060,"Text":"A new draconic power is available at the Cathedral of Dragon Communion"},
{"ID":30061,"Text":"A new draconic power is available at the Cathedral of Dragon Communion"},
{"ID":30062,"Text":"A new draconic power is available at the Cathedral of Dragon Communion"},
{"ID":30063,"Text":"A new draconic power is available at the Cathedral of Dragon Communion"},
{"ID":30064,"Text":"A new draconic power is available at the Cathedral of Dragon Communion"},
{"ID":30065,"Text":"A new draconic power is available at the Cathedral of Dragon Communion"},
{"ID":30066,"Text":"A new draconic power is available at the Cathedral of Dragon Communion"},
{"ID":30080,"Text":"Seal can only be broken by a sealbreaker"},
{"ID":30081,"Text":null},
{"ID":30082,"Text":null},
{"ID":30083,"Text":null},
{"ID":30084,"Text":null},
{"ID":30085,"Text":null},
{"ID":30086,"Text":null},
{"ID":30087,"Text":null},
{"ID":30088,"Text":null},
{"ID":30089,"Text":null},
{"ID":30090,"Text":"Here lie Aurelia and Aureliette,\nwho never saw the stars"},
{"ID":30091,"Text":null},
{"ID":30092,"Text":null},
{"ID":30093,"Text":null},
{"ID":30094,"Text":null},
{"ID":30095,"Text":null},
{"ID":30096,"Text":null},
{"ID":30097,"Text":null},
{"ID":30098,"Text":null},
{"ID":30099,"Text":null},
{"ID":30100,"Text":"You found a simple map.\nCheck in inventory."},
{"ID":30101,"Text":"You found a simple map.\nCheck in inventory."},
{"ID":30102,"Text":null},
{"ID":30103,"Text":null},
{"ID":30104,"Text":null},
{"ID":30105,"Text":null},
{"ID":30106,"Text":null},
{"ID":30107,"Text":null},
{"ID":30108,"Text":null},
{"ID":30109,"Text":null},
{"ID":30110,"Text":"You can now see the Knight of the Great Jar's red summon sign"},
{"ID":30111,"Text":null},
{"ID":30112,"Text":null},
{"ID":30113,"Text":null},
{"ID":30114,"Text":null},
{"ID":30115,"Text":null},
{"ID":30116,"Text":null},
{"ID":30117,"Text":null},
{"ID":30118,"Text":null},
{"ID":30119,"Text":null},
{"ID":30120,"Text":"New items can be purchased from the Twin Maiden Husks"},
{"ID":30121,"Text":null},
{"ID":30122,"Text":null},
{"ID":30123,"Text":null},
{"ID":30124,"Text":null},
{"ID":30125,"Text":null},
{"ID":30126,"Text":null},
{"ID":30127,"Text":null},
{"ID":30128,"Text":null},
{"ID":30129,"Text":null},
{"ID":30130,"Text":"The primal glintstone shudders.\nIt seems Sellen's body has died."},
{"ID":60011,"Text":"Seek three wise beasts"},
{"ID":60012,"Text":null},
{"ID":60013,"Text":null},
{"ID":60014,"Text":null},
{"ID":60015,"Text":null},
{"ID":60016,"Text":null},
{"ID":60017,"Text":null},
{"ID":60018,"Text":null},
{"ID":60019,"Text":null},
{"ID":60020,"Text":null},
{"ID":60021,"Text":"Endow the eyes of the mask in light"},
{"ID":60022,"Text":"Seek three wise beasts"},
{"ID":60023,"Text":null},
{"ID":60024,"Text":null},
{"ID":60025,"Text":null},
{"ID":60026,"Text":"Seek three great wise beasts"},
{"ID":60027,"Text":"Access to those outside of the \nroyal family is strictly forbidden"},
{"ID":60028,"Text":null},
{"ID":60029,"Text":null},
{"ID":60030,"Text":null},
{"ID":60031,"Text":"Touch three phantom crests"},
{"ID":60032,"Text":null},
{"ID":60033,"Text":null},
{"ID":60034,"Text":null},
{"ID":60035,"Text":null},
{"ID":60036,"Text":null},
{"ID":60037,"Text":null},
{"ID":60038,"Text":null},
{"ID":60039,"Text":null},
{"ID":60040,"Text":null},
{"ID":60041,"Text":null},
{"ID":60042,"Text":null},
{"ID":60043,"Text":null},
{"ID":60044,"Text":null},
{"ID":60045,"Text":null},
{"ID":60046,"Text":null},
{"ID":60047,"Text":null},
{"ID":60048,"Text":null},
{"ID":60049,"Text":null},
{"ID":60050,"Text":null},
{"ID":60051,"Text":"Falling snow marks something unseen"},
{"ID":60052,"Text":null},
{"ID":60100,"Text":"Light the four figures in the evergaol"},
{"ID":61010,"Text":"Godrick the Golden, humiliated\nHaving tasted defeat by the Blade of Miquella\nNow on his knees, begging for mercy"},
{"ID":61011,"Text":"Lord Godfrey, at last at the end of his campaign\nHis golden armies unvanquished and unbowed\nYet finds grace lost, tattered and faded"},
{"ID":61012,"Text":"The siege of Castle Morne\nA lone hero fights for his vengeance\nOnly to fall at the hand of Lord Godfrey"},
{"ID":61013,"Text":null},
{"ID":61014,"Text":null},
{"ID":61015,"Text":null},
{"ID":61016,"Text":null},
{"ID":61017,"Text":null},
{"ID":61018,"Text":null},
{"ID":61019,"Text":null},
{"ID":61020,"Text":"This marks Malenia's southward march\nThe Blade of Miquella and her Cleanrot Knights\nGrant her wings never to be clipped"},
{"ID":61021,"Text":"The Second Liurnian War\nNo victory for the golden, nor for the moon\nNo prize but atonement; the birth of a vow"},
{"ID":61022,"Text":"The resting place of the contemptible Cuckoos\nLost in the siege of Caria Manor"},
{"ID":61023,"Text":"The First Liurnian War\nRadagon's glory burns red as his hair"},
{"ID":61024,"Text":null},
{"ID":61025,"Text":null},
{"ID":61026,"Text":null},
{"ID":61027,"Text":null},
{"ID":61028,"Text":null},
{"ID":61029,"Text":null},
{"ID":61030,"Text":"The Routing of the Ancient Dragons\nGodwyn the Golden fought to the last,\nEarning the friendship of dread Fortissax"},
{"ID":61031,"Text":"The First Defense of Leyndell\nA sovereign alliance rots from within\nTraces yet remain of bloody conspiracy"},
{"ID":61032,"Text":"The Second Defense of Leyndell\nThe Fell Omen stacks high the corpses of heroes\nYet the Erdtree remains unshaken"},
{"ID":61033,"Text":"The Assault on Volcano Manor\nThe squalid, the sick, the blasphemous;\na wretched, unending war with no glory"},
{"ID":61034,"Text":null},
{"ID":61035,"Text":null},
{"ID":61036,"Text":null},
{"ID":61037,"Text":null},
{"ID":61038,"Text":null},
{"ID":61039,"Text":null},
{"ID":61040,"Text":"The Battle of Aeonia\nRadahn and Malenia locked in stalemate\nThen, the scarlet rot blooms"},
{"ID":61041,"Text":"The Starscourge Conflict\nRadahn alone holds Sellia secure\nAnd stands tall, to shatter the stars"},
{"ID":61042,"Text":null},
{"ID":61043,"Text":null},
{"ID":61044,"Text":null},
{"ID":61045,"Text":null},
{"ID":61046,"Text":null},
{"ID":61047,"Text":null},
{"ID":61048,"Text":null},
{"ID":61049,"Text":null},
{"ID":61050,"Text":"The War against the Giants\nChampions battle, trolls betray\nFire vanquished, the era of the Erdtree begins"},
{"ID":79000,"Text":"Redeemer Guilbert has invaded!"},
{"ID":79001,"Text":"Redeemer Guilbert died"},
{"ID":79002,"Text":"Redeemer Guilbert returned home"},
{"ID":80000,"Text":"Bloody Finger Hunter Yura was summoned"},
{"ID":80001,"Text":"With his objective accomplished, Bloody Finger Hunter Yura returned to his world"},
{"ID":80002,"Text":"Bloody Finger Hunter Yura has died"},
{"ID":80003,"Text":"Bloody Finger Hunter Yura returned to his world"},
{"ID":80004,"Text":null},
{"ID":80005,"Text":null},
{"ID":80006,"Text":null},
{"ID":80007,"Text":null},
{"ID":80008,"Text":null},
{"ID":80009,"Text":null},
{"ID":80010,"Text":"Bloody Finger Nerijus returned to his world"},
{"ID":80011,"Text":null},
{"ID":80012,"Text":null},
{"ID":80013,"Text":null},
{"ID":80014,"Text":null},
{"ID":80015,"Text":null},
{"ID":80016,"Text":null},
{"ID":80017,"Text":null},
{"ID":80018,"Text":null},
{"ID":80019,"Text":null},
{"ID":80020,"Text":"Invaded by Tanith's Knight!"},
{"ID":80021,"Text":"Tanith's Knight has died"},
{"ID":80601,"Text":"Invade White Mask Varré's world?"},
{"ID":80602,"Text":"Invade Old Knight Istvan's world?"},
{"ID":80603,"Text":"Invade Rileigh the Idle's world?"},
{"ID":80604,"Text":"Invade Juno Hoslow, Knight of Blood's world?"},
{"ID":80605,"Text":"Invade Vargram the Raging Wolf and Errant Sorcerer Wilhelm's world?"},
{"ID":80606,"Text":"Invade Great Horned Tragoth's world?"},
{"ID":80607,"Text":"Be summoned to assist Yura, Hunter of Bloody Fingers?"},
{"ID":80608,"Text":"Be summoned to assist Sorceress Sellen?"},
{"ID":80609,"Text":"Be summoned to challenge Sorceress Sellen?"},
{"ID":80610,"Text":"Be summoned to assist Millicent?"},
{"ID":80611,"Text":"Be summoned to challenge Millicent?"},
{"ID":80800,"Text":"Summoned Castellan Jerren"},
{"ID":80801,"Text":"Castellan Jerren has died"},
{"ID":80802,"Text":"Castellan Jerren returned to his world"},
{"ID":80803,"Text":null},
{"ID":80804,"Text":null},
{"ID":80805,"Text":null},
{"ID":80806,"Text":null},
{"ID":80807,"Text":null},
{"ID":80808,"Text":null},
{"ID":80809,"Text":null},
{"ID":80810,"Text":"Summoned Blaidd the Half-Wolf"},
{"ID":80811,"Text":"Blaidd the Half-Wolf has died"},
{"ID":80812,"Text":"Blaidd the Half-Wolf returned to his world"},
{"ID":80813,"Text":null},
{"ID":80814,"Text":null},
{"ID":80815,"Text":null},
{"ID":80816,"Text":null},
{"ID":80817,"Text":null},
{"ID":80818,"Text":null},
{"ID":80819,"Text":null},
{"ID":80820,"Text":"Summoned Alexander, Warrior Jar"},
{"ID":80821,"Text":"Alexander, Warrior Jar has died"},
{"ID":80822,"Text":"Alexander, Warrior Jar returned to his world"},
{"ID":80823,"Text":null},
{"ID":80824,"Text":null},
{"ID":80825,"Text":null},
{"ID":80826,"Text":null},
{"ID":80827,"Text":null},
{"ID":80828,"Text":null},
{"ID":80829,"Text":null},
{"ID":80830,"Text":"Summoned Great Horned Tragoth"},
{"ID":80831,"Text":"Great Horned Tragoth has died"},
{"ID":80832,"Text":"Great Horned Tragoth returned to his world"},
{"ID":80833,"Text":null},
{"ID":80834,"Text":null},
{"ID":80835,"Text":null},
{"ID":80836,"Text":null},
{"ID":80837,"Text":null},
{"ID":80838,"Text":null},
{"ID":80839,"Text":null},
{"ID":80840,"Text":"Summoned Okina"},
{"ID":80841,"Text":"Okina has died"},
{"ID":80842,"Text":"Okina returned to his world"},
{"ID":80843,"Text":null},
{"ID":80844,"Text":null},
{"ID":80845,"Text":null},
{"ID":80846,"Text":null},
{"ID":80847,"Text":null},
{"ID":80848,"Text":null},
{"ID":80849,"Text":null},
{"ID":80850,"Text":"Summoned Finger Maiden Therolina"},
{"ID":80851,"Text":"Finger Maiden Therolina has died"},
{"ID":80852,"Text":"Finger Maiden Therolina returned to her world"},
{"ID":80853,"Text":null},
{"ID":80854,"Text":null},
{"ID":80855,"Text":null},
{"ID":80856,"Text":null},
{"ID":80857,"Text":null},
{"ID":80858,"Text":null},
{"ID":80859,"Text":null},
{"ID":80860,"Text":"Summoned Lionel the Lionhearted"},
{"ID":80861,"Text":"Lionel the Lionhearted has died"},
{"ID":80862,"Text":"Lionel the Lionhearted returned to his world"},
{"ID":80863,"Text":null},
{"ID":80864,"Text":null},
{"ID":80865,"Text":null},
{"ID":80866,"Text":null},
{"ID":80867,"Text":null},
{"ID":80868,"Text":null},
{"ID":80869,"Text":null},
{"ID":80870,"Text":"Summoned Patches"},
{"ID":80871,"Text":"Patches has died"},
{"ID":80872,"Text":"Patches returned to his world"},
{"ID":90000,"Text":"More awaits you, in the official release"},
{"ID":90001,"Text":null},
{"ID":90002,"Text":null},
{"ID":90003,"Text":null},
{"ID":90004,"Text":null},
{"ID":90005,"Text":null},
{"ID":90006,"Text":null},
{"ID":90007,"Text":null},
{"ID":90008,"Text":null},
{"ID":90009,"Text":null},
{"ID":90010,"Text":"Cannot use this now"},
{"ID":108000,"Text":"Use <?gdsparam@8000?>?"},
{"ID":108001,"Text":null},
{"ID":108002,"Text":null},
{"ID":108003,"Text":null},
{"ID":108004,"Text":null},
{"ID":108005,"Text":null},
{"ID":108006,"Text":null},
{"ID":108007,"Text":null},
{"ID":108008,"Text":null},
{"ID":108009,"Text":null},
{"ID":108010,"Text":"Use <?gdsparam@8010?>?"},
{"ID":108186,"Text":"Use <?gdsparam@8186?>?"},
{"ID":208000,"Text":"<?gdsparam@8000?> was lost with use"},
{"ID":208001,"Text":null},
{"ID":208002,"Text":null},
{"ID":208003,"Text":null},
{"ID":208004,"Text":null},
{"ID":208005,"Text":null},
{"ID":208006,"Text":null},
{"ID":208007,"Text":null},
{"ID":208008,"Text":null},
{"ID":208009,"Text":null},
{"ID":208010,"Text":"Used <?gdsparam@8010?>"},
{"ID":208134,"Text":"Used <?gdsparam@8134?>"},
{"ID":208169,"Text":"Used <?gdsparam@8169?>"},
{"ID":208170,"Text":null},
{"ID":208171,"Text":null},
{"ID":208172,"Text":null},
{"ID":208173,"Text":null},
{"ID":208174,"Text":null},
{"ID":208175,"Text":null},
{"ID":208176,"Text":null},
{"ID":208177,"Text":null},
{"ID":208178,"Text":"Used <?gdsparam@8178?>"},
{"ID":208179,"Text":null},
{"ID":208180,"Text":null},
{"ID":208181,"Text":null},
{"ID":208182,"Text":null},
{"ID":208183,"Text":null},
{"ID":208184,"Text":null},
{"ID":208185,"Text":null},
{"ID":208186,"Text":"<?gdsparam@8186?> was lost with use"},
{"ID":208197,"Text":"Used <?gdsparam@8197?>"},
{"ID":208198,"Text":null},
{"ID":208199,"Text":"Used <?gdsparam@8199?>"},
{"ID":308000,"Text":"No <?gdsparam@8000?> in inventory"},
{"ID":308186,"Text":"No <?gdsparam@8186?> in inventory"},
{"ID":408000,"Text":"Not enough <?gdsparam@8000?>"}
],"Version":2,"BigEndian":false,"Compression":1}}